{
  "generatedAt": "2026-05-11T09:45:39.087Z",
  "sourceFeedUpdatedAt": "2026-05-11T09:45:38.993Z",
  "sourceMode": "rows",
  "workflowMode": "manual-search",
  "notes": [
    "This board is a discovery board, not an auto-buy engine.",
    "No verified eBay candidate pull is required for these rankings; every card should still be searched manually before action."
  ],
  "summary": {
    "totalPlans": 10,
    "prioritySearchCount": 0,
    "watchCount": 7,
    "passCount": 3,
    "manualReviewCount": 0,
    "buyNowCount": 0
  },
  "reviewQueue": [
    {
      "queueRank": 1,
      "code": "EB03-053",
      "name": "Nami (053) (Alternate Art)",
      "setName": "Extra Booster: One Piece Heroine's Edition",
      "action": "watch",
      "confidenceTier": "B",
      "discoveryScore": 72.6,
      "targetBuyPrice": 182.96,
      "idealBuyPrice": 144.39,
      "stretchBuyPrice": 228.42,
      "maxBuyPrice": 268.03,
      "exitZoneLow": 456.96,
      "exitZoneHigh": 511.6,
      "whyInteresting": "PSA 10 spread is huge versus raw market",
      "biggestRisk": "Collectr raw market drifts too far from board pricing",
      "reviewSummary": "Worth checking, but not first in line.",
      "reviewTags": [
        "low-entry",
        "liquid",
        "wide-spread"
      ],
      "collectrLink": "https://app.getcollectr.com/explore/product/672805",
      "priceChartingUrl": "https://www.pricecharting.com/game/one-piece-japanese-extra-booster-heroines-edition/nami-alternate-art-eb03-053"
    }
  ],
  "plans": [
    {
      "sourceRank": 1,
      "code": "EB03-053",
      "name": "Nami (053) (Alternate Art)",
      "setName": "Extra Booster: One Piece Heroine's Edition",
      "rarity": "SR",
      "productId": "672805",
      "priceChartingPath": "/game/one-piece-japanese-extra-booster-heroines-edition/nami-alternate-art-eb03-053",
      "priceChartingUrl": "https://www.pricecharting.com/game/one-piece-japanese-extra-booster-heroines-edition/nami-alternate-art-eb03-053",
      "priceChartingImageUrl": "https://storage.googleapis.com/images.pricecharting.com/jedln4iqj7p2jytz/1600.jpg",
      "marketContext": null,
      "collectrLink": "https://app.getcollectr.com/explore/product/672805",
      "searchScore": 157,
      "rawMarket": 44.5,
      "psa10Market": 564.43,
      "netPsa10Exit": 496.7,
      "gradingCost": 33,
      "costBasis": 110.5,
      "expectedPsaNet": 386.2,
      "profit": 386.2,
      "roiPercent": 349.5,
      "psa10SalesCount": 10,
      "ungradedSalesCount": 30,
      "bgs10SalesCount": 2,
      "collectrRawMarket": 114.59,
      "collectrRawDeltaPercent": 157.51,
      "psa10SpreadMultiple": 12.68,
      "noVerifiedListingPull": true,
      "marketStats": null,
      "discoveryScore": 72.6,
      "buyScore": 72.6,
      "confidenceTier": "B",
      "action": "watch",
      "riskFlags": [
        "collectr_raw_drift",
        "search_only_no_live_pull"
      ],
      "topReasons": [
        "PSA 10 spread is huge versus raw market",
        "PSA 10 sales are liquid enough to matter",
        "Raw sales volume supports manual searching",
        "Profit potential clears a solid bar after fees"
      ],
      "biggestRisk": "collectr_raw_drift",
      "idealBuyPrice": 144.39,
      "targetBuyPrice": 182.96,
      "stretchBuyPrice": 228.42,
      "maxBuyPrice": 268.03,
      "exitZoneLow": 456.96,
      "exitZoneHigh": 511.6,
      "reviewTags": [
        "low-entry",
        "liquid",
        "wide-spread"
      ],
      "reviewSummary": "Worth checking, but not first in line.",
      "rank": 1
    },
    {
      "sourceRank": 2,
      "code": "OP05-119",
      "name": "Monkey.D.Luffy (SP) (Silver)",
      "setName": "A Fist of Divine Speed",
      "rarity": "SEC",
      "productId": "632503",
      "priceChartingPath": "/game/one-piece-japanese-fist-of-divine-speed/monkeydluffy-sp-silver-op05-119",
      "priceChartingUrl": "https://www.pricecharting.com/game/one-piece-japanese-fist-of-divine-speed/monkeydluffy-sp-silver-op05-119",
      "priceChartingImageUrl": "https://storage.googleapis.com/images.pricecharting.com/6qbn7lbtlejdxnqp/1600.jpg",
      "marketContext": null,
      "collectrLink": "https://app.getcollectr.com/explore/product/632503",
      "searchScore": 157,
      "rawMarket": 1094.25,
      "psa10Market": 3474,
      "netPsa10Exit": 3057.12,
      "gradingCost": 79.99,
      "costBasis": 1207.24,
      "expectedPsaNet": 1849.88,
      "profit": 1849.88,
      "roiPercent": 153.23,
      "psa10SalesCount": 9,
      "ungradedSalesCount": 22,
      "bgs10SalesCount": 0,
      "collectrRawMarket": 2599.04,
      "collectrRawDeltaPercent": 137.52,
      "psa10SpreadMultiple": 3.17,
      "noVerifiedListingPull": true,
      "marketStats": null,
      "discoveryScore": 65.3,
      "buyScore": 65.3,
      "confidenceTier": "C",
      "action": "watch",
      "riskFlags": [
        "collectr_raw_drift",
        "high_raw_entry_price",
        "search_only_no_live_pull"
      ],
      "topReasons": [
        "PSA 10 sales are liquid enough to matter",
        "Raw sales volume supports manual searching",
        "Absolute upside is meaningful after fees",
        "Search score says the card is bubbling to the top"
      ],
      "biggestRisk": "collectr_raw_drift",
      "idealBuyPrice": 887.45,
      "targetBuyPrice": 1069.3,
      "stretchBuyPrice": 1272.72,
      "maxBuyPrice": 1440.97,
      "exitZoneLow": 2812.55,
      "exitZoneHigh": 3148.83,
      "reviewTags": [
        "liquid",
        "chase"
      ],
      "reviewSummary": "Worth checking, but not first in line.",
      "rank": 2
    },
    {
      "sourceRank": 3,
      "code": "OP05-119",
      "name": "Monkey.D.Luffy (SP) (Gold)",
      "setName": "A Fist of Divine Speed",
      "rarity": "SEC",
      "productId": "632504",
      "priceChartingPath": "/game/one-piece-japanese-fist-of-divine-speed/monkeydluffy-sp-gold-op05-119",
      "priceChartingUrl": "https://www.pricecharting.com/game/one-piece-japanese-fist-of-divine-speed/monkeydluffy-sp-gold-op05-119",
      "priceChartingImageUrl": "https://storage.googleapis.com/images.pricecharting.com/pfa3b3bcgxrtsggz/1600.jpg",
      "marketContext": null,
      "collectrLink": "https://app.getcollectr.com/explore/product/632504",
      "searchScore": 157,
      "rawMarket": 2767.16,
      "psa10Market": 8159.07,
      "netPsa10Exit": 7179.98,
      "gradingCost": 79.99,
      "costBasis": 2880.15,
      "expectedPsaNet": 4299.83,
      "profit": 4299.83,
      "roiPercent": 149.29,
      "psa10SalesCount": 25,
      "ungradedSalesCount": 22,
      "bgs10SalesCount": 6,
      "collectrRawMarket": 11000,
      "collectrRawDeltaPercent": 297.52,
      "psa10SpreadMultiple": 2.95,
      "noVerifiedListingPull": true,
      "marketStats": null,
      "discoveryScore": 63.8,
      "buyScore": 63.8,
      "confidenceTier": "C",
      "action": "watch",
      "riskFlags": [
        "collectr_raw_drift",
        "high_raw_entry_price",
        "search_only_no_live_pull"
      ],
      "topReasons": [
        "PSA 10 sales are liquid enough to matter",
        "Raw sales volume supports manual searching",
        "Absolute upside is meaningful after fees",
        "Search score says the card is bubbling to the top"
      ],
      "biggestRisk": "collectr_raw_drift",
      "idealBuyPrice": 2192.16,
      "targetBuyPrice": 2619.25,
      "stretchBuyPrice": 3096.99,
      "maxBuyPrice": 3492.14,
      "exitZoneLow": 6605.58,
      "exitZoneHigh": 7395.38,
      "reviewTags": [
        "liquid",
        "chase"
      ],
      "reviewSummary": "Worth checking, but not first in line.",
      "rank": 3
    },
    {
      "sourceRank": 7,
      "code": "OP09-093",
      "name": "Marshall.D.Teach (SP) (Gold)",
      "setName": "Legacy of the Master",
      "rarity": "SR",
      "productId": "646573",
      "priceChartingPath": "/game/one-piece-japanese-legacy-of-the-master/marshalldteach-sp-gold-op09-093",
      "priceChartingUrl": "https://www.pricecharting.com/game/one-piece-japanese-legacy-of-the-master/marshalldteach-sp-gold-op09-093",
      "priceChartingImageUrl": "https://storage.googleapis.com/images.pricecharting.com/hh72dbt75lf3h33t/1600.jpg",
      "marketContext": null,
      "collectrLink": "https://app.getcollectr.com/explore/product/646573",
      "searchScore": 157,
      "rawMarket": 654.46,
      "psa10Market": 1685.29,
      "netPsa10Exit": 1483.06,
      "gradingCost": 79.99,
      "costBasis": 767.45,
      "expectedPsaNet": 715.61,
      "profit": 715.61,
      "roiPercent": 93.24,
      "psa10SalesCount": 15,
      "ungradedSalesCount": 16,
      "bgs10SalesCount": 4,
      "collectrRawMarket": 1417.97,
      "collectrRawDeltaPercent": 116.66,
      "psa10SpreadMultiple": 2.58,
      "noVerifiedListingPull": true,
      "marketStats": null,
      "discoveryScore": 55,
      "buyScore": 55,
      "confidenceTier": "C",
      "action": "watch",
      "riskFlags": [
        "collectr_raw_drift",
        "high_raw_entry_price",
        "search_only_no_live_pull"
      ],
      "topReasons": [
        "PSA 10 sales are liquid enough to matter",
        "Raw sales volume supports manual searching",
        "Absolute upside is meaningful after fees",
        "Search score says the card is bubbling to the top"
      ],
      "biggestRisk": "collectr_raw_drift",
      "idealBuyPrice": 380.59,
      "targetBuyPrice": 465.25,
      "stretchBuyPrice": 559.26,
      "maxBuyPrice": 636.46,
      "exitZoneLow": 1364.42,
      "exitZoneHigh": 1527.55,
      "reviewTags": [
        "liquid",
        "chase"
      ],
      "reviewSummary": "Worth checking, but not first in line.",
      "rank": 4
    },
    {
      "sourceRank": 8,
      "code": "OP09-119",
      "name": "Monkey.D.Luffy (Manga)",
      "setName": "Emperors in the New World",
      "rarity": "SEC",
      "productId": "597068",
      "priceChartingPath": "/game/one-piece-japanese-emperors-in-the-new-world/monkeydluffy-manga-op09-119",
      "priceChartingUrl": "https://www.pricecharting.com/game/one-piece-japanese-emperors-in-the-new-world/monkeydluffy-manga-op09-119",
      "priceChartingImageUrl": "https://storage.googleapis.com/images.pricecharting.com/4ypzweq6uizvmx62/1600.jpg",
      "marketContext": null,
      "collectrLink": "https://app.getcollectr.com/explore/product/597068",
      "searchScore": 155,
      "rawMarket": 741,
      "psa10Market": 1779.85,
      "netPsa10Exit": 1566.27,
      "gradingCost": 79.99,
      "costBasis": 853.99,
      "expectedPsaNet": 712.28,
      "profit": 712.28,
      "roiPercent": 83.41,
      "psa10SalesCount": 30,
      "ungradedSalesCount": 22,
      "bgs10SalesCount": 4,
      "collectrRawMarket": 2110.82,
      "collectrRawDeltaPercent": 184.86,
      "psa10SpreadMultiple": 2.4,
      "noVerifiedListingPull": true,
      "marketStats": null,
      "discoveryScore": 53.1,
      "buyScore": 53.1,
      "confidenceTier": "D",
      "action": "watch",
      "riskFlags": [
        "collectr_raw_drift",
        "high_raw_entry_price",
        "search_only_no_live_pull"
      ],
      "topReasons": [
        "PSA 10 sales are liquid enough to matter",
        "Raw sales volume supports manual searching",
        "Absolute upside is meaningful after fees",
        "Search score says the card is bubbling to the top"
      ],
      "biggestRisk": "collectr_raw_drift",
      "idealBuyPrice": 406.43,
      "targetBuyPrice": 495.84,
      "stretchBuyPrice": 595.13,
      "maxBuyPrice": 676.66,
      "exitZoneLow": 1440.97,
      "exitZoneHigh": 1613.26,
      "reviewTags": [
        "liquid",
        "chase"
      ],
      "reviewSummary": "Worth checking, but not first in line.",
      "rank": 5
    },
    {
      "sourceRank": 5,
      "code": "OP13-119",
      "name": "Portgas.D.Ace (119) (Super Alternate Art)",
      "setName": "Carrying On His Will",
      "rarity": "SEC",
      "productId": "657407",
      "priceChartingPath": "/game/one-piece-japanese-carrying-on-his-will/portgasdace-alternate-art-op13-119",
      "priceChartingUrl": "https://www.pricecharting.com/game/one-piece-japanese-carrying-on-his-will/portgasdace-alternate-art-op13-119",
      "priceChartingImageUrl": "https://storage.googleapis.com/images.pricecharting.com/ksjriwcc42kw6its/1600.jpg",
      "marketContext": null,
      "collectrLink": "https://app.getcollectr.com/explore/product/657407",
      "searchScore": 157,
      "rawMarket": 17.56,
      "psa10Market": 223,
      "netPsa10Exit": 196.24,
      "gradingCost": 33,
      "costBasis": 83.56,
      "expectedPsaNet": 112.68,
      "profit": 112.68,
      "roiPercent": 134.85,
      "psa10SalesCount": 9,
      "ungradedSalesCount": 30,
      "bgs10SalesCount": 0,
      "collectrRawMarket": 1217.59,
      "collectrRawDeltaPercent": 6833.88,
      "psa10SpreadMultiple": 12.7,
      "noVerifiedListingPull": true,
      "marketStats": null,
      "discoveryScore": 51.7,
      "buyScore": 51.7,
      "confidenceTier": "D",
      "action": "watch",
      "riskFlags": [
        "collectr_raw_drift",
        "low_absolute_profit",
        "search_only_no_live_pull"
      ],
      "topReasons": [
        "PSA 10 spread is huge versus raw market",
        "PSA 10 sales are liquid enough to matter",
        "Raw sales volume supports manual searching",
        "Search score says the card is bubbling to the top"
      ],
      "biggestRisk": "collectr_raw_drift",
      "idealBuyPrice": 37.09,
      "targetBuyPrice": 52.32,
      "stretchBuyPrice": 70.28,
      "maxBuyPrice": 85.93,
      "exitZoneLow": 180.54,
      "exitZoneHigh": 202.13,
      "reviewTags": [
        "low-entry",
        "liquid",
        "wide-spread"
      ],
      "reviewSummary": "Worth checking, but not first in line.",
      "rank": 6
    },
    {
      "sourceRank": 4,
      "code": "OP13-119",
      "name": "Portgas.D.Ace (119) (3rd Anniversary)",
      "setName": "Carrying On His Will",
      "rarity": "SEC",
      "productId": "657406",
      "priceChartingPath": "/game/one-piece-japanese-carrying-on-his-will/portgasdace-alternate-art-op13-119",
      "priceChartingUrl": "https://www.pricecharting.com/game/one-piece-japanese-carrying-on-his-will/portgasdace-alternate-art-op13-119",
      "priceChartingImageUrl": "https://storage.googleapis.com/images.pricecharting.com/ksjriwcc42kw6its/1600.jpg",
      "marketContext": null,
      "collectrLink": "https://app.getcollectr.com/explore/product/657406",
      "searchScore": 139,
      "rawMarket": 17.56,
      "psa10Market": 223,
      "netPsa10Exit": 196.24,
      "gradingCost": 33,
      "costBasis": 83.56,
      "expectedPsaNet": 112.68,
      "profit": 112.68,
      "roiPercent": 134.85,
      "psa10SalesCount": 9,
      "ungradedSalesCount": 30,
      "bgs10SalesCount": 0,
      "collectrRawMarket": 5900,
      "collectrRawDeltaPercent": 33499.09,
      "psa10SpreadMultiple": 12.7,
      "noVerifiedListingPull": true,
      "marketStats": null,
      "discoveryScore": 51.7,
      "buyScore": 51.7,
      "confidenceTier": "D",
      "action": "watch",
      "riskFlags": [
        "collectr_raw_drift",
        "low_absolute_profit",
        "search_only_no_live_pull"
      ],
      "topReasons": [
        "PSA 10 spread is huge versus raw market",
        "PSA 10 sales are liquid enough to matter",
        "Raw sales volume supports manual searching",
        "Search score says the card is bubbling to the top"
      ],
      "biggestRisk": "collectr_raw_drift",
      "idealBuyPrice": 37.09,
      "targetBuyPrice": 52.32,
      "stretchBuyPrice": 70.28,
      "maxBuyPrice": 85.93,
      "exitZoneLow": 180.54,
      "exitZoneHigh": 202.13,
      "reviewTags": [
        "low-entry",
        "liquid",
        "wide-spread"
      ],
      "reviewSummary": "Worth checking, but not first in line.",
      "rank": 7
    },
    {
      "sourceRank": 10,
      "code": "OP09-004",
      "name": "Shanks - OP09-004 (SP) (Silver)",
      "setName": "Carrying On His Will",
      "rarity": "SR",
      "productId": "657443",
      "priceChartingPath": "/game/one-piece-carrying-on-his-will/shanks-silver-op09-004",
      "priceChartingUrl": "https://www.pricecharting.com/game/one-piece-carrying-on-his-will/shanks-silver-op09-004",
      "priceChartingImageUrl": "https://storage.googleapis.com/images.pricecharting.com/l4dab4wymc3pqwjw/1600.jpg",
      "marketContext": null,
      "collectrLink": "https://app.getcollectr.com/explore/product/657443",
      "searchScore": 139,
      "rawMarket": 800,
      "psa10Market": 1875,
      "netPsa10Exit": 1650,
      "gradingCost": 79.99,
      "costBasis": 912.99,
      "expectedPsaNet": 737.01,
      "profit": 737.01,
      "roiPercent": 80.72,
      "psa10SalesCount": 3,
      "ungradedSalesCount": 60,
      "bgs10SalesCount": 0,
      "collectrRawMarket": 1000.61,
      "collectrRawDeltaPercent": 25.08,
      "psa10SpreadMultiple": 2.34,
      "noVerifiedListingPull": true,
      "marketStats": null,
      "discoveryScore": 49.7,
      "buyScore": 49.7,
      "confidenceTier": "D",
      "action": "pass",
      "riskFlags": [
        "low_psa10_liquidity",
        "high_raw_entry_price",
        "search_only_no_live_pull"
      ],
      "topReasons": [
        "Raw sales volume supports manual searching",
        "Absolute upside is meaningful after fees",
        "Search score says the card is bubbling to the top"
      ],
      "biggestRisk": "low_psa10_liquidity",
      "idealBuyPrice": 414.02,
      "targetBuyPrice": 501,
      "stretchBuyPrice": 596.24,
      "maxBuyPrice": 673.43,
      "exitZoneLow": 1518,
      "exitZoneHigh": 1699.5,
      "reviewTags": [
        "chase"
      ],
      "reviewSummary": "Pass for now unless the market shifts.",
      "rank": 8
    },
    {
      "sourceRank": 9,
      "code": "EB02-061",
      "name": "Monkey.D.Luffy (061) (Manga)",
      "setName": "Extra Booster: Anime 25th Collection",
      "rarity": "SEC",
      "productId": "629167",
      "priceChartingPath": "/game/one-piece-japanese-extra-booster-anime-25th-collection/monkeydluffy-manga-eb02-061",
      "priceChartingUrl": "https://www.pricecharting.com/game/one-piece-japanese-extra-booster-anime-25th-collection/monkeydluffy-manga-eb02-061",
      "priceChartingImageUrl": "https://storage.googleapis.com/images.pricecharting.com/fd6bdj554r6yzplx/1600.jpg",
      "marketContext": null,
      "collectrLink": "https://app.getcollectr.com/explore/product/629167",
      "searchScore": 155,
      "rawMarket": 855.57,
      "psa10Market": 2013.19,
      "netPsa10Exit": 1771.61,
      "gradingCost": 79.99,
      "costBasis": 968.56,
      "expectedPsaNet": 803.05,
      "profit": 803.05,
      "roiPercent": 82.91,
      "psa10SalesCount": 15,
      "ungradedSalesCount": 8,
      "bgs10SalesCount": 0,
      "collectrRawMarket": 3971.99,
      "collectrRawDeltaPercent": 364.25,
      "psa10SpreadMultiple": 2.35,
      "noVerifiedListingPull": true,
      "marketStats": null,
      "discoveryScore": 49.6,
      "buyScore": 49.6,
      "confidenceTier": "D",
      "action": "pass",
      "riskFlags": [
        "collectr_raw_drift",
        "high_raw_entry_price",
        "search_only_no_live_pull"
      ],
      "topReasons": [
        "PSA 10 sales are liquid enough to matter",
        "Raw sales activity is healthy",
        "Absolute upside is meaningful after fees",
        "Search score says the card is bubbling to the top"
      ],
      "biggestRisk": "collectr_raw_drift",
      "idealBuyPrice": 470.2,
      "targetBuyPrice": 571.34,
      "stretchBuyPrice": 683.63,
      "maxBuyPrice": 775.86,
      "exitZoneLow": 1629.88,
      "exitZoneHigh": 1824.76,
      "reviewTags": [
        "chase"
      ],
      "reviewSummary": "Pass for now unless the market shifts.",
      "rank": 9
    },
    {
      "sourceRank": 6,
      "code": "OP08-001",
      "name": "Tony Tony.Chopper (SPR)",
      "setName": "Extra Booster: Anime 25th Collection",
      "rarity": "L",
      "productId": "629185",
      "priceChartingPath": "/game/one-piece-japanese-extra-booster-anime-25th-collection/tony-tonychopper-op08-001",
      "priceChartingUrl": "https://www.pricecharting.com/game/one-piece-japanese-extra-booster-anime-25th-collection/tony-tonychopper-op08-001",
      "priceChartingImageUrl": "https://storage.googleapis.com/images.pricecharting.com/ghhvjvvuoudwv3jm/1600.jpg",
      "marketContext": null,
      "collectrLink": "https://app.getcollectr.com/explore/product/629185",
      "searchScore": 143,
      "rawMarket": 106,
      "psa10Market": 443.85,
      "netPsa10Exit": 390.59,
      "gradingCost": 33,
      "costBasis": 172,
      "expectedPsaNet": 218.59,
      "profit": 218.59,
      "roiPercent": 127.09,
      "psa10SalesCount": 3,
      "ungradedSalesCount": 22,
      "bgs10SalesCount": 0,
      "collectrRawMarket": 1013.58,
      "collectrRawDeltaPercent": 856.21,
      "psa10SpreadMultiple": 4.19,
      "noVerifiedListingPull": true,
      "marketStats": null,
      "discoveryScore": 38.2,
      "buyScore": 38.2,
      "confidenceTier": "D",
      "action": "pass",
      "riskFlags": [
        "low_psa10_liquidity",
        "collectr_raw_drift",
        "search_only_no_live_pull"
      ],
      "topReasons": [
        "Strong PSA 10 spread versus raw market",
        "Raw sales volume supports manual searching",
        "Profit potential clears a solid bar after fees",
        "Search score says the card is bubbling to the top"
      ],
      "biggestRisk": "collectr_raw_drift",
      "idealBuyPrice": 98.07,
      "targetBuyPrice": 124.5,
      "stretchBuyPrice": 154.78,
      "maxBuyPrice": 180.44,
      "exitZoneLow": 359.34,
      "exitZoneHigh": 402.31,
      "reviewTags": [
        "chase",
        "wide-spread"
      ],
      "reviewSummary": "Pass for now unless the market shifts.",
      "rank": 10
    }
  ]
}